[
  {
    "id": "623dd89bd5a755462b76ccc2",
    "image": "https://ds.rokomari.store/rokomari110/ProductNew20190903/260X372/00ea58560_112222.jpg",
    "price": 418,
    "author": "Jankar Mahbub",
    "book_name": "হাবলুদের প্রোগ্রামিং",
    "book_review": "This books is nicely organized for beginners who want to be a professional web developer. More interestingly this is cover many realitice example. I do recommend those who eagerly wait to start web dream jobs just read its.",
    "author_img":"https://www.facebook.com/photo/?fbid=10154819682976891&set=a.437643276890",
    "Rating":"4.5",
    "gender": "Male"
  },
  {
    "id": "623dd89b2ab68fa712f29160",
    "image": "https://ds.rokomari.store/rokomari110/ProductNew20190903/260X372/0a7334a0a_119934.jpg",
    "price": 315,
    "author": "Tamim Subin",
    "book_name": " কম্পিউটার প্রোগ্রামিং ",
    "book_review": "No doubt this books is completely bangla language which native user can pick the absolute benefits about web devleopment. More interestingly this is cover many realitice example. I do recommend those who eagerly wait to start web dream jobs just read its.",
    "author_img":"https://www.facebook.com/photo/?fbid=10154819682976891&set=a.437643276890",
    "Rating":"3.5",
    "gender": "Male"
  },
  {
    "id": "623dd89b2ab68fa712f29161",
    "image": "https://ds.rokomari.store/rokomari110/ProductNew20190903/260X372/daf9587f9_151491.jpg",
    "price": 315,
    "author": "ডা. মোক্তার হোসেন",
    "book_review": "Todays world is invoking you to move some fancy world where fact is always ignoring some ways this book help you to understand rigth philosophy about web development. More interestingly this is cover many realitice example. I do recommend those who eagerly wait to start web dream jobs just read its.",
    "author_img":"https://www.facebook.com/photo/?fbid=10154819682976891&set=a.437643276890",
    "Rating":"5.0",
    "book_name": " জাভা প্রোগ্রামিং ",
    "gender": "Male"
  },
  {
    "id": "623dd89b2ab68fa712f29162",
    "image": "https://ds.rokomari.store/rokomari110/ProductNew20190903/260X372/c3a744e71_206479.jpg",
    "price": 315,
    "author": "নাসির খান সৈকত",
    "book_review": "This books is nicely organized for beginners who want to be a professional web developer. More interestingly this is cover many realitice example. I do recommend those who eagerly wait to start web dream jobs just read its.",
    "author_img":"https://www.facebook.com/photo/?fbid=10154819682976891&set=a.437643276890",
    "Rating":"4.0",
    "book_name": "পিএচইপি ওয়েব প্রোগ্রামিং ",
    "gender": "Male"
  },
  {
    "id": "623dd89b2ab68fa712f29163",
    "image": "https://ds.rokomari.store/rokomari110/ProductNew20190903/260X372/95530aa52_177444.jpg",
    "price": 315,
    "author": "নাসের ইবনে আফজাল",
    "book_review": "This books is nicely organized for beginners who want to be a professional web developer. More interestingly this is cover many realitice example. I do recommend those who eagerly wait to start web dream jobs just read its.",
    "author_img":"https://www.facebook.com/photo/?fbid=10154819682976891&set=a.437643276890",
    "Rating":"4.0",
    "book_name": " আর প্রোগ্রামিং ",
    "gender": "Male"
  },
  {
    "id": "623dd89b2ab68fa712f29167",
    "image": "https://ds.rokomari.store/rokomari110/ProductNew20190903/260X372/f0836d0b7_158227.jpg",
    "price": 315,
    "author": "ঝংকার মাহবুব",
    "book_review": "This books is nicely organized for beginners who want to be a professional web developer. More interestingly this is cover many realitice example. I do recommend those who eagerly wait to start web dream jobs just read its.",
    "author_img":"https://www.facebook.com/photo/?fbid=10154819682976891&set=a.437643276890",
    "Rating":"5.0",
    "book_name": "প্রোগ্রামিং এর চৌদ্দগোষ্টি",
    "gender": "Male"
  },
  {
    "id": "623dd89b8b786528b3860728",
    "image": "https://ds.rokomari.store/rokomari110/ProductNew20190903/260X372/Python_Programming_310-Zakir_Hossain-0ad51-226630.jpg",
    "price": 519,
    "author": "জাকির হোসেন",
    "book_review": "This books is nicely organized for beginners who want to be a professional web developer. More interestingly this is cover many realitice example. I do recommend those who eagerly wait to start web dream jobs just read its.",
    "author_img":"https://www.facebook.com/photo/?fbid=10154819682976891&set=a.437643276890",
    "Rating":"4.5",
    "book_name": "পাইথন প্রোগ্রামিং ৩.১০",
    "gender": "female"
  },
  {
    "id": "623dd89beece689a5870b3b3",
    "image": "https://ds.rokomari.store/rokomari110/ProductNew20190903/260X372/e53af8191_202772.jpg",
    "price": 230,
    "author": "জুনায়েদ আহম্মদ",
    "book_review": "No doubt this books is completely bangla language which native user can pick the absolute benefits about web devleopment. More interestingly this is cover many realitice example. I do recommend those who eagerly wait to start web dream jobs just read its.",
    "author_img":"https://zonayed.me/static/profile-bd1430b121f195d1f823a8e0b9bf2c46.jpg",
    "Rating":"3.5",
    "book_name": "হাতে কলমে প্রোগ্রামিং",
    "gender": ""
  },
  {
    "id": "623dd89b06cbb4416b42e519",
    "image": "https://ds.rokomari.store/rokomari110/ProductNew20190903/260X372/Programming_er_Addotanta-H_M_Nayem-586bc-228332.jpg",
    "price": 311,
    "author": "H.M Nayeem",
    "book_review": "Todays world is invoking you to move some fancy world where fact is always ignoring some ways this book help you to understand rigth philosophy about web development. recommend those who eagerly wait to start web dream jobs just read its.",
    "author_img":"https://www.facebook.com/photo/?fbid=1542470269485494&set=a.104905539908648",
    "Rating":"5.0",
    "book_name": "প্রোগ্রামিং এর আদ্যোপান্ত",
    "gender": "male"
  }
]